tekek/__init__.py
tekek/models.py
tekek/tekek.py
tekek/types.py
tekek-0.2.6.dist-info/LICENSE
tekek-0.2.6.dist-info/METADATA
tekek-0.2.6.dist-info/WHEEL
tekek-0.2.6.dist-info/top_level.txt
tekek-0.2.6.dist-info/RECORD
