Metadata-Version: 2.1
Name: tekek
Version: 0.2.6
Summary: An Asynchronous Remote and Local Debugging Tools
Home-page: https://github.com/dolano-tours/tekek
Author: Erlangga Ibrahim
Author-email: erlanggaibr2@gmail.com
License: UNKNOWN
Platform: UNKNOWN
Classifier: Programming Language :: Python :: 3.7
Classifier: Programming Language :: Python :: 3.8
Classifier: License :: OSI Approved :: GNU General Public License v3 (GPLv3)
Classifier: Operating System :: OS Independent
Classifier: Development Status :: 3 - Alpha
Classifier: Topic :: Software Development :: Debuggers
Classifier: Topic :: Software Development :: Libraries
Classifier: Topic :: Software Development :: Testing
Classifier: Topic :: Internet :: Log Analysis
Requires-Python: >=3.7
